boto34/__init__.py
boto34/exceptions.py
boto34/aioboto3/__init__.py
boto34/aioboto3/service_factory.py
boto34/aioboto3/session.py
boto34/aioboto3/services/__init__.py
boto34/aioboto3/services/accessanalyzer.py
boto34/aioboto3/services/account.py
boto34/aioboto3/services/acm.py
boto34/aioboto3/services/acm_pca.py
boto34/aioboto3/services/amp.py
boto34/aioboto3/services/amplify.py
boto34/aioboto3/services/amplifybackend.py
boto34/aioboto3/services/amplifyuibuilder.py
boto34/aioboto3/services/apigateway.py
boto34/aioboto3/services/apigatewaymanagementapi.py
boto34/aioboto3/services/apigatewayv2.py
boto34/aioboto3/services/appconfig.py
boto34/aioboto3/services/appconfigdata.py
boto34/aioboto3/services/appfabric.py
boto34/aioboto3/services/appflow.py
boto34/aioboto3/services/appintegrations.py
boto34/aioboto3/services/application_autoscaling.py
boto34/aioboto3/services/application_insights.py
boto34/aioboto3/services/application_signals.py
boto34/aioboto3/services/applicationcostprofiler.py
boto34/aioboto3/services/appmesh.py
boto34/aioboto3/services/apprunner.py
boto34/aioboto3/services/appstream.py
boto34/aioboto3/services/appsync.py
boto34/aioboto3/services/apptest.py
boto34/aioboto3/services/arc_zonal_shift.py
boto34/aioboto3/services/artifact.py
boto34/aioboto3/services/athena.py
boto34/aioboto3/services/auditmanager.py
boto34/aioboto3/services/autoscaling.py
boto34/aioboto3/services/autoscaling_plans.py
boto34/aioboto3/services/b2bi.py
boto34/aioboto3/services/backup.py
boto34/aioboto3/services/backup_gateway.py
boto34/aioboto3/services/backupsearch.py
boto34/aioboto3/services/batch.py
boto34/aioboto3/services/bcm_data_exports.py
boto34/aioboto3/services/bcm_pricing_calculator.py
boto34/aioboto3/services/bedrock.py
boto34/aioboto3/services/bedrock_agent.py
boto34/aioboto3/services/bedrock_agent_runtime.py
boto34/aioboto3/services/bedrock_data_automation.py
boto34/aioboto3/services/bedrock_data_automation_runtime.py
boto34/aioboto3/services/bedrock_runtime.py
boto34-0.1.3.dist-info/METADATA
boto34-0.1.3.dist-info/WHEEL
boto34-0.1.3.dist-info/licenses/LICENSE
boto34-0.1.3.dist-info/RECORD
