Metadata-Version: 2.4
Name: boto34
Version: 0.1.3
Summary: Type annotated AWS SDK for boto3, aiobotocore, and aioboto3.
Project-URL: Homepage, https://github.com/youtype/boto34
Project-URL: Documentation, https://youtype.github.io/boto34/
Project-URL: Repository, https://github.com/youtype/boto34
Project-URL: Changelog, https://github.com/youtype/boto34/releases
Project-URL: Issues, https://github.com/youtype/boto34/issues
Author-email: Vlad Emelianov <vlad.emelianov.nz@gmail.com>
License-File: LICENSE
Keywords: aioboto3,aiobotocore,boto3,mypy,pyright,type-annotations
Classifier: Development Status :: 3 - Alpha
Classifier: Environment :: Console
Classifier: License :: OSI Approved :: MIT License
Classifier: Natural Language :: English
Classifier: Operating System :: OS Independent
Classifier: Programming Language :: Python :: 3
Classifier: Programming Language :: Python :: 3 :: Only
Classifier: Programming Language :: Python :: 3.8
Classifier: Programming Language :: Python :: 3.9
Classifier: Programming Language :: Python :: 3.10
Classifier: Programming Language :: Python :: 3.11
Classifier: Programming Language :: Python :: 3.12
Classifier: Programming Language :: Python :: 3.13
Classifier: Programming Language :: Python :: 3.14
Classifier: Programming Language :: Python :: Implementation :: CPython
Classifier: Topic :: Software Development :: Libraries :: Python Modules
Classifier: Typing :: Typed
Requires-Python: >=3.8
Provides-Extra: aioboto3
Requires-Dist: aioboto3; extra == 'aioboto3'
Requires-Dist: types-aioboto3-lite; extra == 'aioboto3'
Requires-Dist: types-aiobotocore-full; extra == 'aioboto3'
Requires-Dist: types-boto3-lite; extra == 'aioboto3'
Provides-Extra: aiobotocore
Requires-Dist: aiobotocore; extra == 'aiobotocore'
Requires-Dist: types-aiobotocore-full; extra == 'aiobotocore'
Requires-Dist: types-aiobotocore-lite; extra == 'aiobotocore'
Provides-Extra: boto3
Requires-Dist: boto3; extra == 'boto3'
Requires-Dist: types-boto3-full; extra == 'boto3'
Requires-Dist: types-boto3-lite; extra == 'boto3'
